meme_nexus/__init__.py
meme_nexus/exceptions.py
meme_nexus/models.py
meme_nexus/clients/__init__.py
meme_nexus/clients/dexscreener.py
meme_nexus/clients/geckoterminal.py
meme_nexus/utils/draw.py
meme_nexus/utils/format.py
meme_nexus/utils/indicators.py
meme_nexus/utils/draw/__init__.py
meme_nexus/utils/draw/config.py
meme_nexus/utils/draw/elements.py
meme_nexus/utils/draw/main.py
memenexus-0.7.1.dist-info/licenses/LICENSE
memenexus-0.7.1.dist-info/METADATA
memenexus-0.7.1.dist-info/WHEEL
memenexus-0.7.1.dist-info/top_level.txt
memenexus-0.7.1.dist-info/RECORD
