Metadata-Version: 2.4
Name: memeNexus
Version: 0.7.1
Summary: A toolbox for meme trading
Requires-Python: ==3.11.*
License-File: LICENSE
Requires-Dist: apidance>=0.5.0
Requires-Dist: ccxt>=4.4.64
Requires-Dist: httpx>=0.25.2
Requires-Dist: mplfinance>=0.12.10b0
Requires-Dist: smartmoneyconcepts>=0.0.26
Requires-Dist: tenacity>=9.0.0
Dynamic: license-file
